fastprint/__init__.py
fastprint/fastprint.py
fastprint-1.2.dist-info/LICENSE.txt
fastprint-1.2.dist-info/METADATA
fastprint-1.2.dist-info/WHEEL
fastprint-1.2.dist-info/top_level.txt
fastprint-1.2.dist-info/RECORD
